odoo/addons/search_engine_image_thumbnail/README.rst
odoo/addons/search_engine_image_thumbnail/__init__.py
odoo/addons/search_engine_image_thumbnail/__manifest__.py
odoo/addons/search_engine_image_thumbnail/i18n/it.po
odoo/addons/search_engine_image_thumbnail/i18n/search_engine_image_thumbnail.pot
odoo/addons/search_engine_image_thumbnail/models/__init__.py
odoo/addons/search_engine_image_thumbnail/models/ir_attachment.py
odoo/addons/search_engine_image_thumbnail/models/se_backend.py
odoo/addons/search_engine_image_thumbnail/models/se_image_field_thumbnail_size.py
odoo/addons/search_engine_image_thumbnail/models/se_index.py
odoo/addons/search_engine_image_thumbnail/models/se_indexable_record.py
odoo/addons/search_engine_image_thumbnail/models/se_thumbnail.py
odoo/addons/search_engine_image_thumbnail/models/se_thumbnail_size.py
odoo/addons/search_engine_image_thumbnail/readme/CONFIGURE.md
odoo/addons/search_engine_image_thumbnail/readme/CONTEXT.md
odoo/addons/search_engine_image_thumbnail/readme/CONTRIBUTORS.md
odoo/addons/search_engine_image_thumbnail/readme/CREDITS.md
odoo/addons/search_engine_image_thumbnail/readme/DESCRIPTION.md
odoo/addons/search_engine_image_thumbnail/readme/HISTORY.md
odoo/addons/search_engine_image_thumbnail/readme/USAGE.md
odoo/addons/search_engine_image_thumbnail/readme/newsfragments/.gitignore
odoo/addons/search_engine_image_thumbnail/security/se_image_field_thumbnail_size.xml
odoo/addons/search_engine_image_thumbnail/security/se_thumbnail.xml
odoo/addons/search_engine_image_thumbnail/security/se_thumbnail_size.xml
odoo/addons/search_engine_image_thumbnail/static/description/icon.png
odoo/addons/search_engine_image_thumbnail/static/description/index.html
odoo/addons/search_engine_image_thumbnail/tests/__init__.py
odoo/addons/search_engine_image_thumbnail/tests/common.py
odoo/addons/search_engine_image_thumbnail/tests/models.py
odoo/addons/search_engine_image_thumbnail/tests/test_se_multi_image_thumbnail.py
odoo_addon_search_engine_image_thumbnail-16.0.1.0.7.dist-info/METADATA
odoo_addon_search_engine_image_thumbnail-16.0.1.0.7.dist-info/WHEEL
odoo_addon_search_engine_image_thumbnail-16.0.1.0.7.dist-info/top_level.txt
odoo_addon_search_engine_image_thumbnail-16.0.1.0.7.dist-info/RECORD
