Metadata-Version: 2.1
Name: odoo-addon-search_engine_image_thumbnail
Version: 16.0.1.0.7
Summary: Generate thumbnails for binded record
Home-page: https://github.com/OCA/search-engine
Author: ACSONE SA/NV,Odoo Community Association (OCA)
Author-email: support@odoo-community.org
License: AGPL-3
Classifier: Programming Language :: Python
Classifier: Framework :: Odoo
Classifier: Framework :: Odoo :: 16.0
Classifier: License :: OSI Approved :: GNU Affero General Public License v3
Classifier: Development Status :: 3 - Alpha
Requires-Python: >=3.10
Requires-Dist: odoo-addon-base-partition<16.1dev,>=16.0dev
Requires-Dist: odoo-addon-connector-search-engine<16.1dev,>=16.0dev
Requires-Dist: odoo-addon-fs-base-multi-image<16.1dev,>=16.0dev
Requires-Dist: odoo-addon-fs-image-thumbnail<16.1dev,>=16.0dev
Requires-Dist: odoo<16.1dev,>=16.0a
